<?xml version="1.0" encoding="UTF-8"?>
<jmdict>

  <entry entry_uid="1" sequence_id="1000000">
      <reading reading_uid="2" >
          <binary form="raw" >ヽ</binary>
          <pri>spec1</pri>
      </reading>
      <reading reading_uid="3" >
          <binary form="raw" >くりかえし</binary>
      </reading>
      <sense sense_uid="4">
          <pos>&n;</pos>
          <gloss>repetition mark in katakana</gloss>
      </sense>
  </entry>

  <entry entry_uid="5" sequence_id="1000010">
      <reading reading_uid="6" >
          <binary form="raw" >ヾ</binary>
      </reading>
      <reading reading_uid="7" >
          <binary form="raw" >くりかえし</binary>
      </reading>
      <sense sense_uid="8">
          <pos>&n;</pos>
          <gloss>voiced repetition mark in katakana</gloss>
      </sense>
  </entry>

  <entry entry_uid="9" sequence_id="1000020">
      <reading reading_uid="10" >
          <binary form="raw" >ゝ</binary>
      </reading>
      <reading reading_uid="11" >
          <binary form="raw" >くりかえし</binary>
      </reading>
      <sense sense_uid="12">
          <pos>&n;</pos>
          <gloss>repetition mark in hiragana</gloss>
          <field>&food;</field>
      </sense>
  </entry>

  <entry entry_uid="13" sequence_id="1000080">
      <kanji kanji_uid="14" >
          <binary form="raw" >漢数字ゼロ</binary>
      </kanji>
      <reading reading_uid="15" >
          <binary form="raw" >かんすうじゼロ</binary>
      </reading>
      <sense sense_uid="16">
          <pos>&n;</pos>
          <gloss>"kanji" zero</gloss>
          <xref>
              <binary form="raw">○・まる・1</binary>
              <kanji_ref kanji_uid="18">○</kanji_ref>
              <reading_ref reading_uid="20">まる</reading_ref>
              <sense_ref sense_uid="21">circle (sometimes used for zero)</sense_ref>
          </xref>
          <xref>
              <binary form="raw">漢数字</binary>
              <kanji_ref kanji_uid="24">漢数字</kanji_ref>
          </xref>
      </sense>
  </entry>

  <entry entry_uid="17" sequence_id="1000090">
      <kanji kanji_uid="18" >
          <binary form="raw" >○</binary>
          <pri>er4w3r3</pri>
      </kanji>
      <kanji kanji_uid="19" >
          <binary form="raw" >〇</binary>
      </kanji>
      <reading reading_uid="20" >
          <binary form="raw" >まる</binary>
      </reading>
      <sense sense_uid="21">
          <pos>&n;</pos>
          <gloss>circle (sometimes used for zero)</gloss>
      </sense>
      <sense sense_uid="22">
          <pos>&n;</pos>
          <gloss>'correct' (when marking)</gloss>
          <ant>
              <binary form="raw">×・ばつ・1</binary>
              <kanji_ref kanji_uid="28">×</kanji_ref>
              <reading_ref reading_uid="29">ばつ</reading_ref>
              <sense_ref sense_uid="32">x-mark (used to indicate an incorrect answer in a test, etc.)</sense_ref>
          </ant>
      </sense>
  </entry>

  <entry entry_uid="23" sequence_id="1715100">
      <kanji kanji_uid="24" >
          <binary form="raw" >漢数字</binary>
      </kanji>
      <reading reading_uid="25" >
          <binary form="raw" >かんすうじ</binary>
      </reading>
      <sense sense_uid="26">
          <pos>&n;</pos>
          <gloss>Chinese characters which express numbers</gloss>
      </sense>
  </entry>

  <entry entry_uid="27" sequence_id="2197150">
      <kanji kanji_uid="28" >
          <binary form="raw" >×</binary>
      </kanji>
      <reading reading_uid="29" >
          <binary form="raw" >ばつ</binary>
          <info>efwegf43g4</info>
      </reading>
      <reading reading_uid="30" >
          <binary form="raw" >ぺけ</binary>
      </reading>
      <reading reading_uid="31" no_kanji="true">
          <binary form="raw" >ペケ</binary>
      </reading>
      <sense sense_uid="32">
          <pos>&n;</pos>
          <gloss>x-mark (used to indicate an incorrect answer in a test, etc.)</gloss>
      </sense>
      <sense sense_uid="33">
          <reading_ref reading_uid="31">ペケ</reading_ref>
          <pos>&n;</pos>
          <gloss>impossibility</gloss>
          <gloss>futility</gloss>
          <gloss>uselessness</gloss>
          <misc>&uk;</misc>
      </sense>
  </entry>

  <entry entry_uid="34" sequence_id="1010230">
      <kanji kanji_uid="35" >
          <binary form="raw" >半片</binary>
          <info>egufdyewhfyuehwyu</info>
      </kanji>
      <kanji kanji_uid="36" >
          <binary form="raw" >半平</binary>
      </kanji>
      <reading reading_uid="37" >
          <binary form="raw" >はんぺん</binary>
      </reading>
      <reading reading_uid="38" >
          <binary form="raw" >はんぺい</binary>
          <kanji_ref kanji_uid="36">半平</kanji_ref>
      </reading>
      <sense sense_uid="39">
          <pos>&n;</pos>
          <gloss>pounded fish cake</gloss>
          <misc>&uk;</misc>
      </sense>
      <sense sense_uid="40">
          <kanji_ref kanji_uid="35">半片</kanji_ref>
          <pos>&n;</pos>
          <gloss>half a slice</gloss>
          <gloss>half a ticket</gloss>
          <gloss>ticket stub</gloss>
      </sense>
  </entry>

  <entry entry_uid="41" sequence_id="1000230">
      <kanji kanji_uid="42" >
          <binary form="raw" >明かん</binary>
      </kanji>
      <reading reading_uid="43" >
          <binary form="raw" >あかん</binary>
      </reading>
      <reading reading_uid="44" no_kanji="true">
          <binary form="raw" >アカン</binary>
      </reading>
      <sense sense_uid="45">
          <pos>&exp;</pos>
          <gloss>useless</gloss>
          <gloss>no good</gloss>
          <gloss>hopeless</gloss>
          <misc>&uk;</misc>
          <dial>&ksb;</dial>
      </sense>
  </entry>

</jmdict>
